{
  "hero-team.jpg": "https://stpatricks-fll.my.canva.site/_assets/media/<hero-image>.jpg",
  "team-maddox.jpg": "https://stpatricks-fll.my.canva.site/_assets/media/<maddox-image>.jpg",
  "team-zachary.jpg": "https://stpatricks-fll.my.canva.site/_assets/media/<zachary-image>.jpg",
  "team-logan.jpg": "https://stpatricks-fll.my.canva.site/_assets/media/<logan-image>.jpg",
  "team-elessa.jpg": "https://stpatricks-fll.my.canva.site/_assets/media/<elessa-image>.jpg",
  "team-kyan.jpg": "https://stpatricks-fll.my.canva.site/_assets/media/<kyan-image>.jpg",
  "team-elijah.jpg": "https://stpatricks-fll.my.canva.site/_assets/media/<elijah-image>.jpg",
  "innovation-1.jpg": "https://stpatricks-fll.my.canva.site/_assets/media/<innovation-1>.jpg",
  "innovation-2.jpg": "https://stpatricks-fll.my.canva.site/_assets/media/<innovation-2>.jpg",
  "innovation-3.jpg": "https://stpatricks-fll.my.canva.site/_assets/media/<innovation-3>.jpg",
  "stp-campus.jpg": "https://stpatricks-fll.my.canva.site/_assets/media/<campus-image>.jpg"
}
